richxerox.py
richxerox-1.0.0.dist-info/DESCRIPTION.rst
richxerox-1.0.0.dist-info/METADATA
richxerox-1.0.0.dist-info/metadata.json
richxerox-1.0.0.dist-info/RECORD
richxerox-1.0.0.dist-info/top_level.txt
richxerox-1.0.0.dist-info/WHEEL
