Metadata-Version: 2.0
Name: richxerox
Version: 1.0.0
Summary: copy/paste for Mac OS X for rich text (HTML/RTF) rather than plain text
Home-page: https://bitbucket.org/jeunice/richxerox
Author: Jonathan Eunice
Author-email: jonathan.eunice@gmail.com
License: UNKNOWN
Keywords: Mac OS X copy paste clipboard pasteboard rich text RTF HTML
Platform: UNKNOWN
Classifier: Development Status :: 4 - Beta
Classifier: Environment :: MacOS X :: Cocoa
Classifier: License :: OSI Approved :: BSD License
Classifier: Intended Audience :: Developers
Classifier: Programming Language :: Python
Classifier: Programming Language :: Python :: 2.7
Classifier: Programming Language :: Python :: 3
Classifier: Programming Language :: Python :: 3.3
Classifier: Programming Language :: Python :: 3.4
Classifier: Programming Language :: Python :: 3.5
Classifier: Programming Language :: Python :: 3.6
Classifier: Programming Language :: Python :: Implementation :: CPython
Classifier: Topic :: Software Development :: Libraries :: Python Modules
Classifier: Topic :: Text Processing :: Markup
Classifier: Topic :: Text Processing :: Markup :: HTML
